jaconv_domino/__init__.py
jaconv_domino/phoneme.py
jaconv_domino-0.1.2.dist-info/METADATA
jaconv_domino-0.1.2.dist-info/WHEEL
jaconv_domino-0.1.2.dist-info/licenses/LICENSE
jaconv_domino-0.1.2.dist-info/RECORD
