Metadata-Version: 2.4
Name: jaconv-domino
Version: 0.1.2
Summary: Japanese character converter extending jaconv with pydomino phoneme conversion
Project-URL: Homepage, https://github.com/h21465/jaconv-domino
Project-URL: Repository, https://github.com/h21465/jaconv-domino
Project-URL: Documentation, https://github.com/h21465/jaconv-domino#readme
Project-URL: Issues, https://github.com/h21465/jaconv-domino/issues
License: MIT
License-File: LICENSE
Keywords: converter,domino,hiragana,japanese,katakana,lyrics,phoneme
Classifier: Development Status :: 4 - Beta
Classifier: Intended Audience :: Developers
Classifier: License :: OSI Approved :: MIT License
Classifier: Natural Language :: Japanese
Classifier: Operating System :: OS Independent
Classifier: Programming Language :: Python :: 3
Classifier: Programming Language :: Python :: 3.9
Classifier: Programming Language :: Python :: 3.10
Classifier: Programming Language :: Python :: 3.11
Classifier: Programming Language :: Python :: 3.12
Classifier: Topic :: Text Processing :: Linguistic
Requires-Python: >=3.9
Requires-Dist: jaconv>=0.4.0
